{
  "filters": {
    "erosion": {
      "dropletVelocity": 0.7,
      "erosionRate": 0.5,
      "depositeRate": 0.5,
      "dropletsPerChunk": 135,
      "dropletLifetime": 12,
      "dropletVolume": 0.7
    },
    "smoothing": {
      "iterations": 1,
      "smoothingRadius": 1.8,
      "smoothingRate": 0.9
    }
  },
  "structures": {
    "structures": {
      "tconstruct:overworld_sky_island": {
        "spacing": 44,
        "separation": 4,
        "salt": -230904130,
        "disabled": false
      },
      "minecraft:pillager_outposts": {
        "spacing": 32,
        "separation": 8,
        "salt": 165745296,
        "disabled": false
      },
      "tacz_npc:duty": {
        "spacing": 20,
        "separation": 12,
        "salt": 389564243,
        "disabled": false
      },
      "minecraft:ancient_cities": {
        "spacing": 24,
        "separation": 8,
        "salt": 20083232,
        "disabled": false
      },
      "tconstruct:overworld_ocean_island": {
        "spacing": 30,
        "separation": 9,
        "salt": 25988585,
        "disabled": false
      },
      "minecraft:jungle_temples": {
        "spacing": 32,
        "separation": 8,
        "salt": 14357619,
        "disabled": false
      },
      "minecraft:woodland_mansions": {
        "spacing": 80,
        "separation": 20,
        "salt": 10387319,
        "disabled": false
      },
      "spelunkery:cinnabar_wires": {
        "spacing": 24,
        "separation": 8,
        "salt": 20696932,
        "disabled": false
      },
      "minecraft:ocean_monuments": {
        "spacing": 32,
        "separation": 5,
        "salt": 10387313,
        "disabled": false
      },
      "minecraft:mineshafts": {
        "spacing": 1,
        "separation": 0,
        "salt": 0,
        "disabled": false
      },
      "minecraft:swamp_huts": {
        "spacing": 32,
        "separation": 8,
        "salt": 14357620,
        "disabled": false
      },
      "minecraft:villages": {
        "spacing": 34,
        "separation": 8,
        "salt": 10387312,
        "disabled": false
      },
      "minecraft:trail_ruins": {
        "spacing": 34,
        "separation": 8,
        "salt": 83469867,
        "disabled": false
      },
      "minecraft:desert_pyramids": {
        "spacing": 32,
        "separation": 8,
        "salt": 14357617,
        "disabled": false
      },
      "minecraft:ocean_ruins": {
        "spacing": 20,
        "separation": 8,
        "salt": 14357621,
        "disabled": false
      },
      "minecraft:ruined_portals": {
        "spacing": 40,
        "separation": 15,
        "salt": 34222645,
        "disabled": false
      },
      "minecraft:igloos": {
        "spacing": 32,
        "separation": 8,
        "salt": 14357618,
        "disabled": false
      },
      "minecraft:buried_treasures": {
        "spacing": 1,
        "separation": 0,
        "salt": 0,
        "disabled": false
      },
      "minecraft:shipwrecks": {
        "spacing": 24,
        "separation": 4,
        "salt": 165745295,
        "disabled": false
      }
    }
  },
  "miscellaneous": {
    "vanillaLavaLakes": true,
    "vanillaLavaSprings": true,
    "mountainBiomeUsage": 0.4,
    "volcanoBiomeUsage": 0.4,
    "naturalSnowDecorator": true,
    "customBiomeFeatures": true,
    "vanillaSprings": true,
    "oreCompatibleStoneOnly": true,
    "erosionDecorator": true,
    "plainStoneErosion": false,
    "smoothLayerDecorator": true,
    "strataRegionSize": 600,
    "strataDecorator": true
  },
  "terrain": {
    "torridonian": {
      "weight": 2.0,
      "baseScale": 1.0,
      "verticalScale": 1.0,
      "horizontalScale": 1.0
    },
    "mountains": {
      "weight": 3.8554218,
      "baseScale": 1.0,
      "verticalScale": 1.0,
      "horizontalScale": 1.0
    },
    "volcano": {
      "weight": 5.0,
      "baseScale": 1.0,
      "verticalScale": 1.0,
      "horizontalScale": 1.0
    },
    "plateau": {
      "weight": 1.8674699,
      "baseScale": 1.0,
      "verticalScale": 1.0,
      "horizontalScale": 1.0
    },
    "badlands": {
      "weight": 2.068273,
      "baseScale": 1.0,
      "verticalScale": 1.0,
      "horizontalScale": 1.0
    },
    "plains": {
      "weight": 2.0,
      "baseScale": 1.0,
      "verticalScale": 1.0,
      "horizontalScale": 1.0
    },
    "hills": {
      "weight": 2.0,
      "baseScale": 1.0,
      "verticalScale": 1.0,
      "horizontalScale": 1.0
    },
    "dales": {
      "weight": 1.5,
      "baseScale": 1.0,
      "verticalScale": 1.0,
      "horizontalScale": 1.0
    },
    "general": {
      "globalHorizontalScale": 1.4328514,
      "fancyMountains": true,
      "terrainSeedOffset": 1979976640,
      "terrainRegionSize": 2082,
      "globalVerticalScale": 0.98
    },
    "steppe": {
      "weight": 1.0,
      "baseScale": 1.0,
      "verticalScale": 1.0,
      "horizontalScale": 1.0
    }
  },
  "rivers": {
    "branchRivers": {
      "bankWidth": 14,
      "bedWidth": 5,
      "fade": 0.975,
      "bedDepth": 5,
      "minBankHeight": 1,
      "maxBankHeight": 4
    },
    "lakes": {
      "sizeMin": 75,
      "sizeMax": 150,
      "minBankHeight": 2,
      "maxBankHeight": 10,
      "chance": 0.3,
      "minStartDistance": 0.0,
      "maxStartDistance": 0.03,
      "depth": 14
    },
    "wetlands": {
      "chance": 0.6,
      "sizeMin": 175,
      "sizeMax": 225
    },
    "seedOffset": 1326581951,
    "riverCount": 16,
    "mainRivers": {
      "bankWidth": 20,
      "bedWidth": 8,
      "fade": 0.75,
      "bedDepth": 10,
      "minBankHeight": 0,
      "maxBankHeight": 6
    }
  },
  "world": {
    "continent": {
      "continentNoiseOctaves": 4,
      "continentNoiseGain": 0.37650603,
      "continentNoiseLacunarity": 7.451807,
      "continentSkipping": 0.29919678,
      "continentSizeVariance": 0.43825302,
      "continentType": "MULTI_IMPROVED",
      "continentScale": 3002,
      "continentJitter": 0.8242972
    },
    "controlPoints": {
      "shallowOcean": 0.25,
      "beach": 0.327,
      "coast": 0.448,
      "inland": 0.502,
      "islandInland": 0.034136545,
      "islandCoast": 0.07429719,
      "deepOcean": 0.1
    },
    "properties": {
      "worldDepth": 0,
      "seaLevel": 63,
      "spawnType": "CONTINENT_CENTER",
      "worldHeight": 544
    }
  },
  "surface": {
    "erosion": {
      "dirtMin": 94,
      "rockSteepness": 0.65,
      "dirtSteepness": 0.475,
      "screeSteepness": 0.4,
      "rockVariance": 124,
      "rockMin": 106,
      "dirtVariance": 40
    }
  },
  "caves": {
    "ravineCarverProbability": 0.02,
    "largeOreVeins": true,
    "legacyCarverDistribution": false,
    "caveCarverProbability": 0.14285715,
    "deepCaveCarverProbability": 0.07,
    "cheeseCaveProbability": 1.0,
    "spaghettiCaveProbability": 1.0,
    "noodleCaveProbability": 1.0,
    "entranceCaveProbability": 0.12048193,
    "cheeseCaveDepthOffset": 1.5625
  },
  "climate": {
    "temperature": {
      "min": 0.0,
      "max": 1.0,
      "bias": 0.05,
      "seedOffset": -894738528,
      "scale": 5,
      "falloff": 4
    },
    "moisture": {
      "min": 0.0,
      "max": 1.0,
      "bias": 0.0,
      "seedOffset": -1976600834,
      "scale": 7,
      "falloff": 3
    },
    "biomeShape": {
      "biomeSize": 488,
      "macroNoiseSize": 8,
      "biomeWarpScale": 150,
      "biomeWarpStrength": 200
    },
    "biomeEdgeShape": {
      "gain": 0.5,
      "lacunarity": 2.65,
      "strength": 14,
      "type": "CELL_EDGE",
      "scale": 43,
      "octaves": 2
    }
  }
}