{
	"format_version": "1.12.0",
	"minecraft:geometry": [
		{
			"description": {
				"identifier": "geometry.1163x39_shell",
				"texture_width": 16,
				"texture_height": 16,
				"visible_bounds_width": 2,
				"visible_bounds_height": 1.5,
				"visible_bounds_offset": [0, 0.25, 0]
			},
			"bones": [
				{
					"name": "bullet_in_barrel",
					"pivot": [0, -0.0125, -0.65],
					"cubes": [
						{
							"origin": [-0.1183, -0.2981, 0.9375],
							"size": [0.2366, 0.5712, 0.0625],
							"uv": {
								"north": {"uv": [0, 4], "uv_size": [0.5, 0.5]},
								"south": {"uv": [4, 0], "uv_size": [0.5, 0.5]},
								"up": {"uv": [1, 4], "uv_size": [0.5, 0.5]},
								"down": {"uv": [4, 1.5], "uv_size": [0.5, -0.5]}
							}
						},
						{
							"origin": [-0.1183, -0.2981, 0.9375],
							"size": [0.2366, 0.5712, 0.0625],
							"pivot": [0, -0.0125, 0.96875],
							"rotation": [0, 0, 45],
							"uv": {
								"north": {"uv": [2, 4], "uv_size": [0.5, 0.5]},
								"south": {"uv": [4, 2], "uv_size": [0.5, 0.5]},
								"up": {"uv": [3, 4], "uv_size": [0.5, 0.5]},
								"down": {"uv": [4, 3.5], "uv_size": [0.5, -0.5]}
							}
						},
						{
							"origin": [-0.1183, -0.2981, 0.9375],
							"size": [0.2366, 0.5712, 0.0625],
							"pivot": [0, -0.0125, 0.96875],
							"rotation": [0, 0, -45],
							"uv": {
								"north": {"uv": [4, 4], "uv_size": [0.5, 0.5]},
								"south": {"uv": [0, 5], "uv_size": [0.5, 0.5]},
								"up": {"uv": [5, 0], "uv_size": [0.5, 0.5]},
								"down": {"uv": [1, 5.5], "uv_size": [0.5, -0.5]}
							}
						},
						{
							"origin": [-0.1183, -0.2981, 0.9375],
							"size": [0.2366, 0.5712, 0.0625],
							"pivot": [0, -0.0125, 0.96875],
							"rotation": [0, 0, -90],
							"uv": {
								"north": {"uv": [5, 1], "uv_size": [0.5, 0.5]},
								"south": {"uv": [2, 5], "uv_size": [0.5, 0.5]},
								"up": {"uv": [5, 2], "uv_size": [0.5, 0.5]},
								"down": {"uv": [3, 5.5], "uv_size": [0.5, -0.5]}
							}
						},
						{
							"origin": [-0.0994, -0.2525, 0.8125],
							"size": [0.1988, 0.48, 0.125],
							"uv": {
								"up": {"uv": [5, 3], "uv_size": [0.5, 0.5]},
								"down": {"uv": [4, 5.5], "uv_size": [0.5, -0.5]}
							}
						},
						{
							"origin": [-0.0994, -0.2525, 0.8125],
							"size": [0.1988, 0.48, 0.125],
							"pivot": [0, -0.0125, 0.875],
							"rotation": [0, 0, 45],
							"uv": {
								"up": {"uv": [5, 4], "uv_size": [0.5, 0.5]},
								"down": {"uv": [5, 5.5], "uv_size": [0.5, -0.5]}
							}
						},
						{
							"origin": [-0.0994, -0.2525, 0.8125],
							"size": [0.1988, 0.48, 0.125],
							"pivot": [0, -0.0125, 0.875],
							"rotation": [0, 0, -45],
							"uv": {
								"up": {"uv": [0, 6], "uv_size": [0.5, 0.5]},
								"down": {"uv": [6, 0.5], "uv_size": [0.5, -0.5]}
							}
						},
						{
							"origin": [-0.0994, -0.2525, 0.8125],
							"size": [0.1988, 0.48, 0.125],
							"pivot": [0, -0.0125, 0.875],
							"rotation": [0, 0, -90],
							"uv": {
								"up": {"uv": [1, 6], "uv_size": [0.5, 0.5]},
								"down": {"uv": [6, 1.5], "uv_size": [0.5, -0.5]}
							}
						},
						{
							"origin": [-0.1342, -0.3365, -0.4875],
							"size": [0.2684, 0.648, 1.3],
							"pivot": [0, -0.0125, 0.1625],
							"rotation": [0, 0, -90],
							"uv": {
								"south": {"uv": [2, 6], "uv_size": [0.5, 0.5]},
								"up": {"uv": [0, 0], "uv_size": [0.5, 1.5]},
								"down": {"uv": [1, 1.5], "uv_size": [0.5, -1.5]}
							}
						},
						{
							"origin": [-0.1342, -0.3365, -0.4875],
							"size": [0.2684, 0.648, 1.3],
							"pivot": [0, -0.0125, 0.1625],
							"rotation": [0, 0, -45],
							"uv": {
								"south": {"uv": [6, 2], "uv_size": [0.5, 0.5]},
								"up": {"uv": [0, 2], "uv_size": [0.5, 1.5]},
								"down": {"uv": [2, 1.5], "uv_size": [0.5, -1.5]}
							}
						},
						{
							"origin": [-0.1342, -0.3365, -0.4875],
							"size": [0.2684, 0.648, 1.3],
							"pivot": [0, -0.0125, 0.1625],
							"rotation": [0, 0, 45],
							"uv": {
								"south": {"uv": [3, 6], "uv_size": [0.5, 0.5]},
								"up": {"uv": [1, 2], "uv_size": [0.5, 1.5]},
								"down": {"uv": [2, 3.5], "uv_size": [0.5, -1.5]}
							}
						},
						{
							"origin": [-0.1342, -0.3365, -0.4875],
							"size": [0.2684, 0.648, 1.3],
							"uv": {
								"south": {"uv": [6, 3], "uv_size": [0.5, 0.5]},
								"up": {"uv": [3, 0], "uv_size": [0.5, 1.5]},
								"down": {"uv": [3, 3.5], "uv_size": [0.5, -1.5]}
							}
						},
						{
							"origin": [-0.122, -0.307, -0.875],
							"size": [0.244, 0.589, 0.325],
							"uv": {
								"north": {"uv": [4, 6], "uv_size": [0.5, 0.5]},
								"up": {"uv": [6, 4], "uv_size": [0.5, 0.5]},
								"down": {"uv": [5, 6.5], "uv_size": [0.5, -0.5]}
							}
						},
						{
							"origin": [-0.122, -0.307, -0.875],
							"size": [0.244, 0.589, 0.325],
							"pivot": [0, -0.0125, -0.7125],
							"rotation": [0, 0, -45],
							"uv": {
								"north": {"uv": [6, 5], "uv_size": [0.5, 0.5]},
								"up": {"uv": [6, 6], "uv_size": [0.5, 0.5]},
								"down": {"uv": [0, 7.5], "uv_size": [0.5, -0.5]}
							}
						},
						{
							"origin": [-0.122, -0.307, -0.875],
							"size": [0.244, 0.589, 0.325],
							"pivot": [0, -0.0125, -0.7125],
							"rotation": [0, 0, -90],
							"uv": {
								"north": {"uv": [7, 0], "uv_size": [0.5, 0.5]},
								"up": {"uv": [1, 7], "uv_size": [0.5, 0.5]},
								"down": {"uv": [7, 1.5], "uv_size": [0.5, -0.5]}
							}
						},
						{
							"origin": [-0.122, -0.307, -0.875],
							"size": [0.244, 0.589, 0.325],
							"pivot": [0, -0.0125, -0.7125],
							"rotation": [0, 0, 45],
							"uv": {
								"north": {"uv": [2, 7], "uv_size": [0.5, 0.5]},
								"up": {"uv": [7, 2], "uv_size": [0.5, 0.5]},
								"down": {"uv": [3, 7.5], "uv_size": [0.5, -0.5]}
							}
						},
						{
							"origin": [-0.0728, 0.17196, -0.4228],
							"size": [0.012, 0.0125, 0.07018],
							"pivot": [0, -0.0125, -0.7125],
							"rotation": [25.60752, -9.03482, -4.30418],
							"uv": {
								"up": {"uv": [7, 3], "uv_size": [0.5, 0.5]}
							}
						},
						{
							"origin": [0.0608, 0.17196, -0.4228],
							"size": [0.012, 0.0125, 0.07018],
							"pivot": [0, -0.0125, -0.7125],
							"rotation": [25.60752, 9.03482, 4.30418],
							"uv": {
								"up": {"uv": [4, 7], "uv_size": [0.5, 0.5]}
							}
						},
						{
							"origin": [-0.122, 0.17196, -0.43984],
							"size": [0.244, 0.0125, 0.06911],
							"pivot": [0, -0.0125, -0.7125],
							"rotation": [25.2673, 0, 0],
							"uv": {
								"up": {"uv": [7, 4], "uv_size": [0.5, 0.5]}
							}
						},
						{
							"origin": [-0.0728, 0.17196, -0.4228],
							"size": [0.012, 0.0125, 0.07018],
							"pivot": [0, -0.0125, -0.7125],
							"rotation": [25.60752, -9.03482, 40.69582],
							"uv": {
								"up": {"uv": [5, 7], "uv_size": [0.5, 0.5]}
							}
						},
						{
							"origin": [0.0608, 0.17196, -0.4228],
							"size": [0.012, 0.0125, 0.07018],
							"pivot": [0, -0.0125, -0.7125],
							"rotation": [25.60752, 9.03482, 49.30418],
							"uv": {
								"up": {"uv": [7, 5], "uv_size": [0.5, 0.5]}
							}
						},
						{
							"origin": [-0.122, 0.17196, -0.43984],
							"size": [0.244, 0.0125, 0.06911],
							"pivot": [0, -0.0125, -0.7125],
							"rotation": [25.2673, 0, 45],
							"uv": {
								"up": {"uv": [6, 7], "uv_size": [0.5, 0.5]}
							}
						},
						{
							"origin": [-0.0728, 0.17196, -0.4228],
							"size": [0.012, 0.0125, 0.07018],
							"pivot": [0, -0.0125, -0.7125],
							"rotation": [25.60752, -9.03482, 85.69582],
							"uv": {
								"up": {"uv": [7, 6], "uv_size": [0.5, 0.5]}
							}
						},
						{
							"origin": [0.0608, 0.17196, -0.4228],
							"size": [0.012, 0.0125, 0.07018],
							"pivot": [0, -0.0125, -0.7125],
							"rotation": [25.60752, 9.03482, 94.30418],
							"uv": {
								"up": {"uv": [7, 7], "uv_size": [0.5, 0.5]}
							}
						},
						{
							"origin": [-0.122, 0.17196, -0.43984],
							"size": [0.244, 0.0125, 0.06911],
							"pivot": [0, -0.0125, -0.7125],
							"rotation": [25.2673, 0, 90],
							"uv": {
								"up": {"uv": [0, 8], "uv_size": [0.5, 0.5]}
							}
						},
						{
							"origin": [-0.0728, 0.17196, -0.4228],
							"size": [0.012, 0.0125, 0.07018],
							"pivot": [0, -0.0125, -0.7125],
							"rotation": [25.60752, -9.03482, 130.69582],
							"uv": {
								"up": {"uv": [8, 0], "uv_size": [0.5, 0.5]}
							}
						},
						{
							"origin": [0.0608, 0.17196, -0.4228],
							"size": [0.012, 0.0125, 0.07018],
							"pivot": [0, -0.0125, -0.7125],
							"rotation": [25.60752, 9.03482, 139.30418],
							"uv": {
								"up": {"uv": [1, 8], "uv_size": [0.5, 0.5]}
							}
						},
						{
							"origin": [-0.122, 0.17196, -0.43984],
							"size": [0.244, 0.0125, 0.06911],
							"pivot": [0, -0.0125, -0.7125],
							"rotation": [25.2673, 0, 135],
							"uv": {
								"up": {"uv": [8, 1], "uv_size": [0.5, 0.5]}
							}
						},
						{
							"origin": [-0.0728, 0.17196, -0.4228],
							"size": [0.012, 0.0125, 0.07018],
							"pivot": [0, -0.0125, -0.7125],
							"rotation": [25.60752, -9.03482, 175.69582],
							"uv": {
								"up": {"uv": [2, 8], "uv_size": [0.5, 0.5]}
							}
						},
						{
							"origin": [0.0608, 0.17196, -0.4228],
							"size": [0.012, 0.0125, 0.07018],
							"pivot": [0, -0.0125, -0.7125],
							"rotation": [25.60752, 9.03482, -175.69582],
							"uv": {
								"up": {"uv": [8, 2], "uv_size": [0.5, 0.5]}
							}
						},
						{
							"origin": [-0.122, 0.17196, -0.43984],
							"size": [0.244, 0.0125, 0.06911],
							"pivot": [0, -0.0125, -0.7125],
							"rotation": [25.2673, 0, 180],
							"uv": {
								"up": {"uv": [3, 8], "uv_size": [0.5, 0.5]}
							}
						},
						{
							"origin": [-0.0728, 0.17196, -0.4228],
							"size": [0.012, 0.0125, 0.07018],
							"pivot": [0, -0.0125, -0.7125],
							"rotation": [25.60752, -9.03482, -139.30418],
							"uv": {
								"up": {"uv": [8, 3], "uv_size": [0.5, 0.5]}
							}
						},
						{
							"origin": [0.0608, 0.17196, -0.4228],
							"size": [0.012, 0.0125, 0.07018],
							"pivot": [0, -0.0125, -0.7125],
							"rotation": [25.60752, 9.03482, -130.69582],
							"uv": {
								"up": {"uv": [4, 8], "uv_size": [0.5, 0.5]}
							}
						},
						{
							"origin": [-0.122, 0.17196, -0.43984],
							"size": [0.244, 0.0125, 0.06911],
							"pivot": [0, -0.0125, -0.7125],
							"rotation": [25.2673, 0, -135],
							"uv": {
								"up": {"uv": [8, 4], "uv_size": [0.5, 0.5]}
							}
						},
						{
							"origin": [-0.0728, 0.17196, -0.4228],
							"size": [0.012, 0.0125, 0.07018],
							"pivot": [0, -0.0125, -0.7125],
							"rotation": [25.60752, -9.03482, -94.30418],
							"uv": {
								"up": {"uv": [5, 8], "uv_size": [0.5, 0.5]}
							}
						},
						{
							"origin": [0.0608, 0.17196, -0.4228],
							"size": [0.012, 0.0125, 0.07018],
							"pivot": [0, -0.0125, -0.7125],
							"rotation": [25.60752, 9.03482, -85.69582],
							"uv": {
								"up": {"uv": [8, 5], "uv_size": [0.5, 0.5]}
							}
						},
						{
							"origin": [-0.122, 0.17196, -0.43984],
							"size": [0.244, 0.0125, 0.06911],
							"pivot": [0, -0.0125, -0.7125],
							"rotation": [25.2673, 0, -90],
							"uv": {
								"up": {"uv": [6, 8], "uv_size": [0.5, 0.5]}
							}
						},
						{
							"origin": [-0.0728, 0.17196, -0.4228],
							"size": [0.012, 0.0125, 0.07018],
							"pivot": [0, -0.0125, -0.7125],
							"rotation": [25.60752, -9.03482, -49.30418],
							"uv": {
								"up": {"uv": [8, 6], "uv_size": [0.5, 0.5]}
							}
						},
						{
							"origin": [0.0608, 0.17196, -0.4228],
							"size": [0.012, 0.0125, 0.07018],
							"pivot": [0, -0.0125, -0.7125],
							"rotation": [25.60752, 9.03482, -40.69582],
							"uv": {
								"up": {"uv": [7, 8], "uv_size": [0.5, 0.5]}
							}
						},
						{
							"origin": [-0.122, 0.17196, -0.43984],
							"size": [0.244, 0.0125, 0.06911],
							"pivot": [0, -0.0125, -0.7125],
							"rotation": [25.2673, 0, -45],
							"uv": {
								"up": {"uv": [8, 7], "uv_size": [0.5, 0.5]}
							}
						}
					]
				}
			]
		}
	]
}